[{"name":"Insecticide pour insectes rampants 200ml - BRAVO","price":"21,95 DH"},{"name":"Insecticide pour insectes rampants 750ml - BRAVO","price":"43,95 DH"},{"name":"Insecticide pour insectes rampants 400ml - BRAVO","price":"30,95 DH"},{"name":"Aérosol insecticide parfumé au citron tous insectes 250ml - ZENTEK","price":"28,50 DH"},{"name":"Insecticide aérosol double action tous insectes 500ml - ORO","price":"37,95 DH"},{"name":"Insecticide pour insectes volants parfum citron 400ml - BRAVO","price":"30,95 DH"},{"name":"Insecticide aérosol double action tous insectes 300ml - ORO","price":"26,95 DH"},{"name":"Insecticide aérosol tous insectes Jaune citron 200 ml - ZENTEK","price":"12,95 DH"},{"name":"Insecticide pour insectes volants parfum citron 750ml - BRAVO","price":"43,95 DH"},{"name":"Insecticide aérosol double action tous insectes 400ml - ORO","price":"31,95 DH"},{"name":"Tue insectes 6W MOK-220 - DENWA","price":"299,00 DH"},{"name":"Four posable CMFO 45S - CANDY","price":"1 499,00 DH"},{"name":"Tube gel insecticide 20g - ZENTEK","price":"59,95 DH"},{"name":"Piège à insectes mural MOK-320 3W - DENWA","price":"199,00 DH"},{"name":"Insecticide aérosol double action parfumé citron vert tous insectes 200ml - ORO","price":"19,50 DH"},{"name":"Insecticide liquide anti cafards 400ml - BENGAL","price":"54,50 DH"},{"name":"Aérosol contre les insectes rampants 360ml - BAYGON","price":"30,50 DH"},{"name":"Seringue gel insecticide anti-cafard 35g - ZENTEK","price":"100,95 DH"},{"name":"Aérosol insecticide volant 5 en 1 300ml - RAID","price":"20,95 DH"},{"name":"Micro-ondes INSTANT TRONIC 20L 1200W blanc - TAURUS","price":"1 290,00 DH"},{"name":"DUO HOTTE + PLAQUE DE CUISSON 75SPX/SXD+HTCFT610/2S - CANDY"},{"name":"Ecouteur avec micro IN-EAR EARPHONES EO-IA500 - SAMSUNG","price":"99,00 DH"},{"name":"Ordinateur portable IP5 I5 15,6 8/512 W11 bleu - LENOVO","price":"6 699,00 DH"},{"name":"Démêleur instant restore 350ml - SUNSILK","price":"36,50 DH"},{"name":"Ordinateur portable IP5 I7 14 16/512 W11 gris - LENOVO","price":"9 999,00 DH"},{"name":"2 dentifrices Colgate Optic White Instant 75ml","price":"42,25 DH"},{"name":"Nouilles instantanées 250g - KHAYRAT","price":"15,50 DH"},{"name":"Nouilles instantanées saveur bœuf 85g - ROKA","price":"5,95 DH"},{"name":"Dentifrice optic white instant 75ml - COLGATE","price":"35,95 DH"}]